<annotation>
  <folder>KAIST Multispectral Ped Benchmark</folder>
  <filename>set08/V002/I00270</filename>
  <source>
    <database>KAIST pedestrian</database>
    <annotation>KAIST pedestrian</annotation>
    <image>KAIST pedestrian</image>
    <url>https://soonminhwang.github.io/rgbt-ped-detection/</url>
  </source>
  <size>
    <width>640</width>
    <height>512</height>
    <depth>4</depth>
  </size>
  <segmented>0</segmented>
  <object>
    <name>person</name>
    <bndbox>
      <x>569</x>
      <y>208</y>
      <w>31</w>
      <h>92</h>
    </bndbox>
    <pose>unknown</pose>
    <truncated>0</truncated>
    <difficult>0</difficult>
    <occlusion>0</occlusion>
  </object>
  <object>
    <name>person</name>
    <bndbox>
      <x>126</x>
      <y>213</y>
      <w>27</w>
      <h>51</h>
    </bndbox>
    <pose>unknown</pose>
    <truncated>0</truncated>
    <difficult>0</difficult>
    <occlusion>2</occlusion>
  </object>
  <object>
    <name>person</name>
    <bndbox>
      <x>109</x>
      <y>214</y>
      <w>38</w>
      <h>60</h>
    </bndbox>
    <pose>unknown</pose>
    <truncated>0</truncated>
    <difficult>0</difficult>
    <occlusion>0</occlusion>
  </object>
  <object>
    <name>person</name>
    <bndbox>
      <x>96</x>
      <y>211</y>
      <w>36</w>
      <h>63</h>
    </bndbox>
    <pose>unknown</pose>
    <truncated>0</truncated>
    <difficult>0</difficult>
    <occlusion>0</occlusion>
  </object>
  <object>
    <name>person</name>
    <bndbox>
      <x>558</x>
      <y>212</y>
      <w>33</w>
      <h>81</h>
    </bndbox>
    <pose>unknown</pose>
    <truncated>0</truncated>
    <difficult>0</difficult>
    <occlusion>1</occlusion>
  </object>
</annotation>
