<annotation>
  <folder>KAIST Multispectral Ped Benchmark</folder>
  <filename>set06/V001/I00436</filename>
  <source>
    <database>KAIST pedestrian</database>
    <annotation>KAIST pedestrian</annotation>
    <image>KAIST pedestrian</image>
    <url>https://soonminhwang.github.io/rgbt-ped-detection/</url>
  </source>
  <size>
    <width>640</width>
    <height>512</height>
    <depth>4</depth>
  </size>
  <segmented>0</segmented>
  <object>
    <name>person</name>
    <bndbox>
      <x>357</x>
      <y>212</y>
      <w>55</w>
      <h>103</h>
    </bndbox>
    <pose>unknown</pose>
    <truncated>0</truncated>
    <difficult>0</difficult>
    <occlusion>0</occlusion>
  </object>
  <object>
    <name>person</name>
    <bndbox>
      <x>401</x>
      <y>214</y>
      <w>39</w>
      <h>94</h>
    </bndbox>
    <pose>unknown</pose>
    <truncated>0</truncated>
    <difficult>0</difficult>
    <occlusion>0</occlusion>
  </object>
  <object>
    <name>person</name>
    <bndbox>
      <x>14</x>
      <y>189</y>
      <w>50</w>
      <h>73</h>
    </bndbox>
    <pose>unknown</pose>
    <truncated>0</truncated>
    <difficult>0</difficult>
    <occlusion>0</occlusion>
  </object>
  <object>
    <name>person</name>
    <bndbox>
      <x>111</x>
      <y>214</y>
      <w>35</w>
      <h>74</h>
    </bndbox>
    <pose>unknown</pose>
    <truncated>0</truncated>
    <difficult>0</difficult>
    <occlusion>0</occlusion>
  </object>
  <object>
    <name>person</name>
    <bndbox>
      <x>156</x>
      <y>216</y>
      <w>34</w>
      <h>67</h>
    </bndbox>
    <pose>unknown</pose>
    <truncated>0</truncated>
    <difficult>0</difficult>
    <occlusion>0</occlusion>
  </object>
  <object>
    <name>person</name>
    <bndbox>
      <x>132</x>
      <y>216</y>
      <w>29</w>
      <h>66</h>
    </bndbox>
    <pose>unknown</pose>
    <truncated>0</truncated>
    <difficult>0</difficult>
    <occlusion>0</occlusion>
  </object>
  <object>
    <name>person</name>
    <bndbox>
      <x>472</x>
      <y>220</y>
      <w>34</w>
      <h>64</h>
    </bndbox>
    <pose>unknown</pose>
    <truncated>0</truncated>
    <difficult>0</difficult>
    <occlusion>0</occlusion>
  </object>
  <object>
    <name>person</name>
    <bndbox>
      <x>235</x>
      <y>215</y>
      <w>26</w>
      <h>62</h>
    </bndbox>
    <pose>unknown</pose>
    <truncated>0</truncated>
    <difficult>0</difficult>
    <occlusion>0</occlusion>
  </object>
  <object>
    <name>person</name>
    <bndbox>
      <x>557</x>
      <y>205</y>
      <w>27</w>
      <h>56</h>
    </bndbox>
    <pose>unknown</pose>
    <truncated>0</truncated>
    <difficult>0</difficult>
    <occlusion>2</occlusion>
  </object>
</annotation>
