<annotation>
  <folder>KAIST Multispectral Ped Benchmark</folder>
  <filename>set06/V001/I00548</filename>
  <source>
    <database>KAIST pedestrian</database>
    <annotation>KAIST pedestrian</annotation>
    <image>KAIST pedestrian</image>
    <url>https://soonminhwang.github.io/rgbt-ped-detection/</url>
  </source>
  <size>
    <width>640</width>
    <height>512</height>
    <depth>4</depth>
  </size>
  <segmented>0</segmented>
  <object>
    <name>person</name>
    <bndbox>
      <x>95</x>
      <y>217</y>
      <w>48</w>
      <h>98</h>
    </bndbox>
    <pose>unknown</pose>
    <truncated>0</truncated>
    <difficult>0</difficult>
    <occlusion>0</occlusion>
  </object>
  <object>
    <name>person</name>
    <bndbox>
      <x>160</x>
      <y>214</y>
      <w>37</w>
      <h>103</h>
    </bndbox>
    <pose>unknown</pose>
    <truncated>0</truncated>
    <difficult>0</difficult>
    <occlusion>0</occlusion>
  </object>
  <object>
    <name>person</name>
    <bndbox>
      <x>124</x>
      <y>211</y>
      <w>35</w>
      <h>109</h>
    </bndbox>
    <pose>unknown</pose>
    <truncated>0</truncated>
    <difficult>0</difficult>
    <occlusion>0</occlusion>
  </object>
  <object>
    <name>person</name>
    <bndbox>
      <x>437</x>
      <y>232</y>
      <w>58</w>
      <h>170</h>
    </bndbox>
    <pose>unknown</pose>
    <truncated>0</truncated>
    <difficult>0</difficult>
    <occlusion>0</occlusion>
  </object>
  <object>
    <name>person</name>
    <bndbox>
      <x>423</x>
      <y>217</y>
      <w>39</w>
      <h>100</h>
    </bndbox>
    <pose>unknown</pose>
    <truncated>0</truncated>
    <difficult>0</difficult>
    <occlusion>2</occlusion>
  </object>
  <object>
    <name>person</name>
    <bndbox>
      <x>414</x>
      <y>206</y>
      <w>45</w>
      <h>68</h>
    </bndbox>
    <pose>unknown</pose>
    <truncated>0</truncated>
    <difficult>0</difficult>
    <occlusion>2</occlusion>
  </object>
  <object>
    <name>person</name>
    <bndbox>
      <x>188</x>
      <y>211</y>
      <w>38</w>
      <h>92</h>
    </bndbox>
    <pose>unknown</pose>
    <truncated>0</truncated>
    <difficult>0</difficult>
    <occlusion>0</occlusion>
  </object>
</annotation>
