<annotation>
  <folder>KAIST Multispectral Ped Benchmark</folder>
  <filename>set11/V000/I01197</filename>
  <source>
    <database>KAIST pedestrian</database>
    <annotation>KAIST pedestrian</annotation>
    <image>KAIST pedestrian</image>
    <url>https://soonminhwang.github.io/rgbt-ped-detection/</url>
  </source>
  <size>
    <width>640</width>
    <height>512</height>
    <depth>4</depth>
  </size>
  <segmented>0</segmented>
  <object>
    <name>person</name>
    <bndbox>
      <x>78</x>
      <y>246</y>
      <w>44</w>
      <h>124</h>
    </bndbox>
    <pose>unknown</pose>
    <truncated>0</truncated>
    <difficult>0</difficult>
    <occlusion>0</occlusion>
  </object>
  <object>
    <name>person</name>
    <bndbox>
      <x>122</x>
      <y>242</y>
      <w>39</w>
      <h>136</h>
    </bndbox>
    <pose>unknown</pose>
    <truncated>0</truncated>
    <difficult>0</difficult>
    <occlusion>0</occlusion>
  </object>
  <object>
    <name>person</name>
    <bndbox>
      <x>361</x>
      <y>230</y>
      <w>34</w>
      <h>77</h>
    </bndbox>
    <pose>unknown</pose>
    <truncated>0</truncated>
    <difficult>0</difficult>
    <occlusion>0</occlusion>
  </object>
  <object>
    <name>person</name>
    <bndbox>
      <x>378</x>
      <y>222</y>
      <w>29</w>
      <h>76</h>
    </bndbox>
    <pose>unknown</pose>
    <truncated>0</truncated>
    <difficult>0</difficult>
    <occlusion>0</occlusion>
  </object>
  <object>
    <name>person</name>
    <bndbox>
      <x>2</x>
      <y>231</y>
      <w>70</w>
      <h>261</h>
    </bndbox>
    <pose>unknown</pose>
    <truncated>0</truncated>
    <difficult>0</difficult>
    <occlusion>2</occlusion>
  </object>
</annotation>
